[  
   {  
      "id":1,
      "name":"Vijay",
      "title":"Mr",
      "phone":"991234567",
      "ext":"53600",
      "fax":"991234567",
      "email":"vindodhd@gmail.com"
   },
   {  
      "id":2,
      "name":"Saurabh",
      "title":"Mr",
      "phone":"993456789",
      "ext":"53602",
      "fax":"993456789",
      "email":"saurabh@gmail.com"
   },
   {  
      "id":3,
      "name":"Reyaz",
      "title":"Mr",
      "phone":"994567890",
      "ext":"53602",
      "fax":"994567890",
      "email":"reyaz@gmail.com"
   },
   {  
      "id":4,
      "name":"Jithu",
      "title":"Mr",
      "phone":"987654345",
      "ext":"78637",
      "fax":"76487",
      "email":"jithu@gmail.com"
   },
   {  
      "id":5,
      "name":"Nagu",
      "title":"Mr",
      "phone":"987454345",
      "ext":"78337",
      "fax":"72487",
      "email":"nagu@gmail.com"
   }
]